{
  "id": "2012",
  "name": "Miami Valley Xpress 2012",
  "year": 2024,
  "teamImageUrl": "",
  "players": [
    {
      "name": "Annie White",
      "number": "4",
      "position": "C/Utility",
      "height": "",
      "bats": "R",
      "throws": "R",
      "town": "Kettering",
      "school": "Fairmont",
      "gradYear": 2030,
      "imageUrl": "assets/teams/2012/4.png"
    },
    {
      "name": "Elly King",
      "number": "10",
      "position": "P/2nd/OF",
      "height": "",
      "bats": "R",
      "throws": "R",
      "town": "Centerville",
      "school": "Centerville",
      "gradYear": 2031,
      "imageUrl": "assets/teams/2012/6.png"
    },
    {
      "name": "Bristol DeWitt",
      "number": "12",
      "position": "3rd/C",
      "height": "",
      "bats": "R",
      "throws": "R",
      "town": "Fairborn",
      "school": "Fairborn",
      "gradYear": 2030,
      "imageUrl": "assets/teams/2012/10.png"
    },
    {
      "name": "Hailey Russell",
      "number": "31",
      "position": "2nd/OF",
      "height": "",
      "bats": "R",
      "throws": "R",
      "town": "",
      "school": "",
      "gradYear": 2030,
      "imageUrl": "assets/teams/2012/31.png"
    },
    {
      "name": "Kendall Young",
      "number": "42",
      "position": "C/Utility",
      "height": "",
      "bats": "R",
      "throws": "R",
      "town": "Kettering",
      "school": "Fairmont",
      "gradYear": 2031,
      "imageUrl": "assets/teams/2012/42.png"
    },
    {
      "name": "Aubrey Stitzel",
      "number": "16",
      "position": "SS",
      "height": "",
      "bats": "R",
      "throws": "R",
      "town": "",
      "school": "",
      "gradYear": 2030,
      "imageUrl": "assets/teams/2012/16.png"
    },
    {
      "name": "Ahriyia Brown",
      "number": "24",
      "position": "C/Utility",
      "height": "",
      "bats": "R",
      "throws": "R",
      "town": "",
      "school": "",
      "gradYear": 2030,
      "imageUrl": "assets/teams/2012/24.png"
    },
    {
      "name": "Olivia Lane",
      "number": "6",
      "position": "P/1/OF",
      "height": "",
      "bats": "L",
      "throws": "L",
      "town": "",
      "school": "",
      "gradYear": 2031,
      "imageUrl": "assets/teams/2012/6.png"
    },
    {
      "name": "Addy Hornung",
      "number": "11",
      "position": "P/Utility",
      "height": "",
      "bats": "L",
      "throws": "R",
      "town": "",
      "school": "",
      "gradYear": 2030,
      "imageUrl": "assets/teams/2012/11.png"
    }
  ],
  "schedule": [],
  "coaches": [
    {
      "name": "Joanna White",
      "position": "Head Coach",
      "email": "miamivalleyexpress2012@gmail.com",
      "phone": "9379740454",
      "imageUrl": "assets/teams/defaultpfp.jpg"
    },
    {
      "name": "Jim McCord",
      "position": "Asst Coach / Defense",
      "email": "miamivalleyexpress2012@gmail.com",
      "phone": "9379740585",
      "imageUrl": "assets/teams/defaultpfp.jpg"
    },
    {
      "name": "Tori Mcpherson",
      "position": "Asst Coach",
      "email": "miamivalleyexpress2012@gmail.com",
      "phone": "",
      "imageUrl": "assets/teams/defaultpfp.jpg"
    }
  ]
}
